README.rst
setup.py
d1Login.egg-info/PKG-INFO
d1Login.egg-info/SOURCES.txt
d1Login.egg-info/dependency_links.txt
d1Login.egg-info/entry_points.txt
d1Login.egg-info/requires.txt
d1Login.egg-info/top_level.txt
d1_certificate/__init__.py
d1_certificate/__main__.py
d1_certificate/certinfo.py
d1_certificate/grid_shib.py