Metadata-Version: 1.1
Name: d1Login
Version: 1.0.1
Summary: Tool to assist with certificate login for DataONE
Home-page: https://github.com/DataONEorg/d1Login
Author: Dave Vieglais
Author-email: datadavev@users.noreply.github.com
License: Apache 2.0
Keywords: openssl,DataONE,certificate,authentication
Platform: UNKNOWN
Classifier: Development Status :: 4 - Beta
Classifier: Environment :: Console
Classifier: Intended Audience :: Developers
Classifier: Topic :: Scientific/Engineering
Classifier: License :: OSI Approved :: Apache Software License
Classifier: Programming Language :: Python :: 2
Classifier: Programming Language :: Python :: 2.7
Classifier: Programming Language :: Python :: 3
Classifier: Programming Language :: Python :: 3.5
